spec_utils/__init__.py
spec_utils/clients/__init__.py
spec_utils/clients/certronic/__init__.py
spec_utils/clients/certronic/async_client.py
spec_utils/clients/certronic/client.py
spec_utils/clients/exactian/__init__.py
spec_utils/clients/exactian/client.py
spec_utils/clients/http.py
spec_utils/clients/infocontrol/__init__.py
spec_utils/clients/infocontrol/client.py
spec_utils/clients/infocontrol/models.py
spec_utils/clients/nettime6/__init__.py
spec_utils/clients/nettime6/async_client.py
spec_utils/clients/nettime6/client.py
spec_utils/clients/nettime6/query.py
spec_utils/clients/specmanager_api/__init__.py
spec_utils/clients/specmanager_api/async_client.py
spec_utils/clients/specmanager_api/client.py
spec_utils/clients/specmanager_api/const.py
spec_utils/clients/specmanager_db/__init__.py
spec_utils/clients/specmanager_db/client.py
spec_utils/clients/t3_gateway/__init__.py
spec_utils/clients/t3_gateway/async_client.py
spec_utils/clients/t3_gateway/client.py
spec_utils/clients/visma/__init__.py
spec_utils/clients/visma/async_client.py
spec_utils/clients/visma/client.py
spec_utils/clients/visma/utils.py
spec_utils/clients/wdms/__init__.py
spec_utils/clients/wdms/client.py
spec_utils/clients/wdms_api/__init__.py
spec_utils/clients/wdms_api/async_client.py
spec_utils/clients/wdms_api/client.py
spec_utils/clients/wdms_api/typos.py
spec_utils/schemas/__init__.py
spec_utils/schemas/base.py
spec_utils/schemas/certronic.py
spec_utils/schemas/specmanager.py
spec_utils/schemas/wdms.py
spec_utils/schemas/wdms_api.py
spec_utils/utils.py
spec_utils-0.35.16.dist-info/METADATA
spec_utils-0.35.16.dist-info/WHEEL
spec_utils-0.35.16.dist-info/licenses/LICENSE
spec_utils-0.35.16.dist-info/RECORD
