Metadata-Version: 2.4
Name: spec-utils
Version: 0.35.16
Summary: Python package to consume SPEC SA and third-party apps
License: GNU General Public License v3 or later (GPLv3+)
License-File: LICENSE
Author: Lucas Lucyk
Author-email: llucyk@grupospec.com
Requires-Python: >=3.10,<4.0
Classifier: License :: Other/Proprietary License
Classifier: Programming Language :: Python :: 3
Classifier: Programming Language :: Python :: 3.10
Classifier: Programming Language :: Python :: 3.11
Classifier: Programming Language :: Python :: 3.12
Classifier: Programming Language :: Python :: 3.13
Classifier: Programming Language :: Python :: 3.14
Requires-Dist: SQLAlchemy (>=2.0.0,<3.0.0)
Requires-Dist: aiohttp (>=3.0.0,<4.0.0)
Requires-Dist: pandas (>=2.0.0,<3.0.0)
Requires-Dist: pydantic (>=2.0.0,<3.0.0)
Requires-Dist: pydantic-settings (>=2.0.0,<3.0.0)
Requires-Dist: requests (>=2.0.0,<3.0.0)
Project-URL: Repository, https://gitlab.com/spec-sa-ar/spec-utils
